CSMHP/CSMHP_class.py
CSMHP/__init__.py
CSMHP/optimize_wrapper.py
CSMHP/utils.py
CSMHP/utils_old.py
CSMHP-0.1.5.dist-info/LICENSE.txt
CSMHP-0.1.5.dist-info/METADATA
CSMHP-0.1.5.dist-info/WHEEL
CSMHP-0.1.5.dist-info/top_level.txt
CSMHP-0.1.5.dist-info/RECORD
