Metadata-Version: 2.2
Name: CSMHP
Version: 0.1.5
Summary: Cluster-based Superposed Marked Hawkes Process
Home-page: https://github.com/ross1456/CSMHP.git
Author: Ross
Author-email: rosscooper@link.cuhk.edu.hk
License: MIT
Classifier: Programming Language :: Python :: 3
Classifier: License :: OSI Approved :: MIT License
Classifier: Operating System :: OS Independent
Requires-Python: >=3.8
License-File: LICENSE.txt
Requires-Dist: numpy
Requires-Dist: pandas
Requires-Dist: scipy
Requires-Dist: scikit-learn
Dynamic: author
Dynamic: author-email
Dynamic: classifier
Dynamic: description
Dynamic: description-content-type
Dynamic: home-page
Dynamic: license
Dynamic: requires-dist
Dynamic: requires-python
Dynamic: summary
